{
  "dependencies": [
    "Verticality"
  ],
  "tasks": {},
  "rewards": {},
  "display": {
    "subtitle": {
      "translate": "Place stairs each way you like!"
    },
    "description": [
      "Stairs have much more capacity for unique geometry!"
    ],
    "groups": {
      "Building": {
        "position": [
          -69,
          8
        ]
      }
    },
    "icon": {
      "item": {
        "id": "minecraft:purpur_stairs",
        "count": 1
      },
      "type": "heracles:item"
    },
    "icon_background": "heracles:textures/gui/quest_backgrounds/rounded_squares.png",
    "title": {
      "translate": "Stairs"
    }
  },
  "settings": {
    "showDependencyArrow": true,
    "repeatable": false,
    "autoClaimRewards": false,
    "individual_progress": false,
    "hidden": "LOCKED",
    "unlockNotification": false
  }
}