{
	"elements": [
		{
			"weight": 1.0,
			"key": "ruby_exchange:admin_exchange_block"
		},
		{
			"weight": 1.0,
			"key": "ruby_exchange:admin_trade_block"
		},
		{
			"weight": 1.0,
			"key": "ruby_exchange:deepslate_ruby_ore"
		},
		{
			"weight": 1.0,
			"key": "ruby_exchange:exchange_block"
		},
		{
			"weight": 1.0,
			"key": "ruby_exchange:ruby"
		},
		{
			"weight": 1.0,
			"key": "ruby_exchange:ruby_block"
		},
		{
			"weight": 1.0,
			"key": "ruby_exchange:ruby_card"
		},
		{
			"weight": 1.0,
			"key": "ruby_exchange:ruby_ore"
		},
		{
			"weight": 1.0,
			"key": "ruby_exchange:trade_block"
		}
	]
}
