{
	"elements": [
		{
			"weight": 1.0,
			"key": "xercamusic:banjo"
		},
		{
			"weight": 1.0,
			"key": "xercamusic:bass_guitar"
		},
		{
			"weight": 1.0,
			"key": "xercamusic:cello"
		},
		{
			"weight": 1.0,
			"key": "xercamusic:cymbal"
		},
		{
			"weight": 1.0,
			"key": "xercamusic:drum"
		},
		{
			"weight": 1.0,
			"key": "xercamusic:drum_kit"
		},
		{
			"weight": 1.0,
			"key": "xercamusic:flute"
		},
		{
			"weight": 1.0,
			"key": "xercamusic:french_horn"
		},
		{
			"weight": 1.0,
			"key": "xercamusic:god"
		},
		{
			"weight": 1.0,
			"key": "xercamusic:guitar"
		},
		{
			"weight": 1.0,
			"key": "xercamusic:harp_mc"
		},
		{
			"weight": 1.0,
			"key": "xercamusic:lyre"
		},
		{
			"weight": 1.0,
			"key": "xercamusic:metronome"
		},
		{
			"weight": 1.0,
			"key": "xercamusic:music_box"
		},
		{
			"weight": 1.0,
			"key": "xercamusic:music_sheet"
		},
		{
			"weight": 1.0,
			"key": "xercamusic:oboe"
		},
		{
			"weight": 1.0,
			"key": "xercamusic:piano"
		},
		{
			"weight": 1.0,
			"key": "xercamusic:redstone_guitar"
		},
		{
			"weight": 1.0,
			"key": "xercamusic:sansula"
		},
		{
			"weight": 1.0,
			"key": "xercamusic:saxophone"
		},
		{
			"weight": 1.0,
			"key": "xercamusic:tubular_bell"
		},
		{
			"weight": 1.0,
			"key": "xercamusic:violin"
		},
		{
			"weight": 1.0,
			"key": "xercamusic:xylophone"
		}
	]
}
